composipy/__init__.py
composipy/version.py
composipy/core/__init__.py
composipy/core/material.py
composipy/core/property.py
composipy/core/strength.py
composipy/core/structure.py
composipy/nastranapi/__init__.py
composipy/nastranapi/pcomp_generator.py
composipy/optimize/__init__.py
composipy/optimize/_maximize_buckling.py
composipy/optimize/_minimize_panel_weight.py
composipy/optimize/utils.py
composipy/pre_integrated_component/_S.py
composipy/pre_integrated_component/__init__.py
composipy/pre_integrated_component/_ii_F.py
composipy/pre_integrated_component/build_k.py
composipy/pre_integrated_component/functions.py
composipy/pre_integrated_component/write_pre_integrated_terms.py
composipy/pre_integrated_component/write_shape_function.py
composipy/utils/__init__.py
composipy/utils/validators.py
composipy-1.6.0.dist-info/licenses/LICENSE
composipy-1.6.0.dist-info/METADATA
composipy-1.6.0.dist-info/WHEEL
composipy-1.6.0.dist-info/top_level.txt
composipy-1.6.0.dist-info/RECORD
